LICENSE
blacksheep_prometheus/__init__.py
blacksheep_prometheus/middleware.py
blacksheep_prometheus/py.typed
blacksheep_prometheus/view.py
blacksheep_prometheus-0.1.8.dist-info/LICENSE
blacksheep_prometheus-0.1.8.dist-info/WHEEL
blacksheep_prometheus-0.1.8.dist-info/METADATA
blacksheep_prometheus-0.1.8.dist-info/RECORD
