Metadata-Version: 2.1
Name: blacksheep-prometheus
Version: 0.1.8
Summary: Prometheus integration for blacksheep
Home-page: https://github.com/Cdayz/blacksheep-prometheus
License: MIT
Keywords: blacksheep,prometheus,metrics
Author: Nikita Tomchik
Author-email: cdayz@yandex.ru
Requires-Python: >=3.7,<4.0
Classifier: Development Status :: 5 - Production/Stable
Classifier: Intended Audience :: Developers
Classifier: License :: OSI Approved :: MIT License
Classifier: Programming Language :: Python :: 3
Classifier: Programming Language :: Python :: 3.10
Classifier: Programming Language :: Python :: 3.7
Classifier: Programming Language :: Python :: 3.8
Classifier: Programming Language :: Python :: 3.9
Classifier: Topic :: Internet :: WWW/HTTP :: HTTP Servers
Classifier: Topic :: Software Development
Classifier: Topic :: Software Development :: Libraries
Requires-Dist: blacksheep (>=1.0.7)
Requires-Dist: prometheus-client (>=0.11.0)
Project-URL: Repository, https://github.com/Cdayz/blacksheep-prometheus
